md2ipynb/__init__.py
md2ipynb/__main__.py
md2ipynb/apply.py
md2ipynb/apply_test.py
md2ipynb/new_notebook.py
md2ipynb/new_notebook_test.py
md2ipynb/testing.py
md2ipynb/util.py
md2ipynb/util_test.py
md2ipynb/read/__init__.py
md2ipynb/read/github_sample.py
md2ipynb/read/github_sample_test.py
md2ipynb/read/lines.py
md2ipynb/read/lines_test.py
md2ipynb/read/markdown_loader.py
md2ipynb/read/markdown_loader_test.py
md2ipynb/read/paragraphs.py
md2ipynb/read/paragraphs_test.py
md2ipynb/read/sections.py
md2ipynb/read/sections_test.py
md2ipynb/steps/__init__.py
md2ipynb/steps/filter_classes.py
md2ipynb/steps/filter_classes_test.py
md2ipynb/steps/flatten.py
md2ipynb/steps/flatten_test.py
md2ipynb/steps/imports.py
md2ipynb/steps/imports_test.py
md2ipynb/steps/open_in_colab.py
md2ipynb/steps/open_in_colab_test.py
md2ipynb/steps/paragraphs_to_cells.py
md2ipynb/steps/paragraphs_to_cells_test.py
md2ipynb/steps/view_the_docs.py
md2ipynb/steps/view_the_docs_test.py
md2ipynb-0.2.1.dist-info/LICENSE
md2ipynb-0.2.1.dist-info/METADATA
md2ipynb-0.2.1.dist-info/WHEEL
md2ipynb-0.2.1.dist-info/entry_points.txt
md2ipynb-0.2.1.dist-info/top_level.txt
md2ipynb-0.2.1.dist-info/RECORD
