Metadata-Version: 2.1
Name: md2ipynb
Version: 0.2.1
Summary: Markdown to Jupyter Notebook converter.
Home-page: https://github.com/davidcavazos/md2ipynb
Author: David Cavazos
Author-email: dcavazosw@gmail.com
License: UNKNOWN
Platform: UNKNOWN
Classifier: Development Status :: 3 - Alpha
Classifier: Intended Audience :: Developers
Classifier: License :: OSI Approved :: Apache Software License
Classifier: Operating System :: OS Independent
Classifier: Programming Language :: Python :: 2.7
Classifier: Programming Language :: Python :: 3
Classifier: Topic :: Software Development :: Build Tools
Classifier: Topic :: Software Development :: Code Generators
Classifier: Topic :: Software Development :: Compilers
Requires-Dist: Jinja2
Requires-Dist: html2md
Requires-Dist: nbformat
Requires-Dist: requests
